frame_lustre/Framework.py
frame_lustre/__init__.py
frame_lustre/dropDowBox_Value.py
frame_lustre/test.py
frame_lustre/test1.py
UI_Framework-0.3.dist-info/METADATA
UI_Framework-0.3.dist-info/WHEEL
UI_Framework-0.3.dist-info/top_level.txt
UI_Framework-0.3.dist-info/RECORD
